src/proxima/__init__.py
src/proxima/app/__init__.py
src/proxima/app/checks.py
src/proxima/app/core.py
src/proxima/app/exceptions.py
src/proxima/app/link.py
src/proxima/app/package.py
src/proxima/app/resolve.py
src/proxima/celery/__init__.py
src/proxima/celery/celery.py
src/proxima/celery/ffmpeg/__init__.py
src/proxima/celery/ffmpeg/ffmpeg_process.py
src/proxima/celery/ffmpeg/utils.py
src/proxima/celery/launch_workers.py
src/proxima/celery/shared.py
src/proxima/celery/tasks.py
src/proxima/cli/__init__.py
src/proxima/cli/main.py
src/proxima/cli/queue.py
src/proxima/settings/__init__.py
src/proxima/settings/default_settings.toml
src/proxima/settings/manager.py
src/proxima/settings/user_settings.toml
src/proxima/tests/test_checks.py
src/proxima/types/__init__.py
src/proxima/types/batch.py
src/proxima/types/job.py
src/proxima/types/media_pool_index.py
dr_proxima-1.0.7.dist-info/LICENSE
dr_proxima-1.0.7.dist-info/METADATA
dr_proxima-1.0.7.dist-info/WHEEL
dr_proxima-1.0.7.dist-info/entry_points.txt
dr_proxima-1.0.7.dist-info/RECORD
