Metadata-Version: 2.1
Name: dr-proxima
Version: 1.0.7
Summary: Transcode source media in DaVinci Resolve using multiple machines. Great for quickly creating proxies without interrupting work.
Home-page: https://in03.github.com/proxima
License: MIT
Keywords: DaVinci Resolve,Scripting,Proxy,Transcode,Distributed,Batch
Author: Caleb Trevatt
Author-email: sk188okj@duck.com
Requires-Python: >=3.10.0,<4.0.0
Classifier: License :: OSI Approved :: MIT License
Classifier: Operating System :: OS Independent
Classifier: Programming Language :: Python :: 3
Classifier: Programming Language :: Python :: 3.10
Classifier: Programming Language :: Python :: 3.11
Classifier: Programming Language :: Python :: 3
Requires-Dist: GitPython (>=3.1.30,<4.0.0)
Requires-Dist: celery (>=5.1.2,<6.0.0)
Requires-Dist: click (>=8.1.3,<9.0.0)
Requires-Dist: deepdiff (>=5.7.0,<6.0.0)
Requires-Dist: notify-py (>=0.3.42,<0.4.0)
Requires-Dist: pydantic[dotenv] (>=1.10.4,<2.0.0)
Requires-Dist: pydavinci-18 (>=0.3.1,<0.4.0)
Requires-Dist: pyfiglet (>=0.8.post1,<0.9)
Requires-Dist: pymediainfo (>=5.1.0,<6.0.0)
Requires-Dist: pytest (>=7.2.0,<8.0.0)
Requires-Dist: redis (>=3.5.3,<4.0.0)
Requires-Dist: requests (>=2.26.0,<3.0.0)
Requires-Dist: rich (>=10.12.0,<11.0.0)
Requires-Dist: rtoml (>=0.9.0,<0.10.0)
Requires-Dist: ruamel.yaml (>=0.17.17,<0.18.0)
Requires-Dist: schema (>=0.7.5,<0.8.0)
Requires-Dist: semver (>=2.13.0,<3.0.0)
Requires-Dist: shellingham (>=1.5.0.post1,<2.0.0)
Requires-Dist: shortuuid (>=1.0.9,<2.0.0)
Requires-Dist: termynal (>=0.2.0,<0.3.0)
Requires-Dist: typer[rich] (>=0.7.0,<0.8.0)
Requires-Dist: yaspin (>=2.1.0,<3.0.0)
Project-URL: Repository, https://github.com/in03/proxima
